besmarts/sample.py
besmarts/smiles.py
besmarts/worker.py
besmarts/assign/hierarchy_assign_native.py
besmarts/cluster/cluster_assignment.py
besmarts/cluster/cluster_objective.py
besmarts/cluster/cluster_optimization.py
besmarts/codecs/codec_native.py
besmarts/core/arrays.py
besmarts/core/assignments.py
besmarts/core/chem.py
besmarts/core/clusters.py
besmarts/core/codecs.py
besmarts/core/compute.py
besmarts/core/configs.py
besmarts/core/db.py
besmarts/core/geometry.py
besmarts/core/graph_visitors.py
besmarts/core/graphs.py
besmarts/core/hierarchies.py
besmarts/core/hierarchy_merge.py
besmarts/core/logs.py
besmarts/core/mapper.py
besmarts/core/optimization.py
besmarts/core/perception.py
besmarts/core/primitives.py
besmarts/core/resolve.py
besmarts/core/returns.py
besmarts/core/rulesets.py
besmarts/core/splits.py
besmarts/core/topology.py
besmarts/core/tree_iterators.py
besmarts/core/tree_visitors.py
besmarts/core/trees.py
besmarts-0.1.0.dist-info/METADATA
besmarts-0.1.0.dist-info/WHEEL
besmarts-0.1.0.dist-info/top_level.txt
besmarts-0.1.0.dist-info/RECORD
