Metadata-Version: 2.2
Name: besmarts
Version: 0.1.0
Summary: Binary Encoded SMARTS
Home-page: https://github.com/trevorgokey/besmarts
Author: Trevor Gokey
Author-email: tgokey@uci.edu
License: MIT
Classifier: Programming Language :: Python :: 3.6
Classifier: Programming Language :: Python :: 3.7
Classifier: Programming Language :: Python :: 3.8
Classifier: Programming Language :: Python :: 3.9
Classifier: Programming Language :: Python :: 3.10
Classifier: Programming Language :: Python :: 3.11
Classifier: Programming Language :: Python :: 3.12
Classifier: License :: OSI Approved :: MIT License
Classifier: Operating System :: OS Independent
Requires-Python: >=3.6
Provides-Extra: rdkit
Requires-Dist: besmarts-rdkit; extra == "rdkit"
Provides-Extra: scipy
Requires-Dist: besmarts-scipy; extra == "scipy"
Provides-Extra: openmm
Requires-Dist: besmarts-openmm; extra == "openmm"
Dynamic: author
Dynamic: author-email
Dynamic: classifier
Dynamic: description
Dynamic: description-content-type
Dynamic: home-page
Dynamic: license
Dynamic: provides-extra
Dynamic: requires-python
Dynamic: summary
